README.md
setup.py
Dandelyon.egg-info/PKG-INFO
Dandelyon.egg-info/SOURCES.txt
Dandelyon.egg-info/dependency_links.txt
Dandelyon.egg-info/top_level.txt
dandelyon/__init__.py
dandelyon/dandelyon.py
dandelyon/deprecators.py
tests/__init__.py
tests/test_deprecate.py