Metadata-Version: 2.1
Name: Dandelyon
Version: 0.2.5
Summary: A library for handling deprecation warnings and events.
Home-page: https://github.com/andrewgy8/dandelyon
Author: Andrew Graham-Yooll
Author-email: andrewgy8@gmail.com
License: UNKNOWN
Keywords: deprecate deprecation decorator
Platform: UNKNOWN
Requires-Python: >=3
